enebootools/__init__.py
enebootools/__init__.pyc
enebootools/entry_points.py
enebootools/parseargs.py
enebootools/parseargs.pyc
enebootools/assembler/__init__.py
enebootools/assembler/config.py
enebootools/assembler/copylib.py
enebootools/assembler/database.py
enebootools/assembler/databasemodels.py
enebootools/assembler/featureconfig.py
enebootools/assembler/kobjects.py
enebootools/assembler/mypeewee.py
enebootools/assembler/save_auto.py
enebootools/autoconfig/__init__.py
enebootools/autoconfig/autoconfig.py
enebootools/autoconfig/parsers.py
enebootools/config/__init__.py
enebootools/crypto/__init__.py
enebootools/crypto/main.py
enebootools/crypto/certificates/CA_Partners_Gestiweb.crt
enebootools/crypto/certificates/CA_Test_Partners.crt
enebootools/crypto/certificates/Eneboo_Open_Source_ERP.crt
enebootools/crypto/certificates/Partner_Test.crt
enebootools/crypto/certificates/Partner_Test.pem
enebootools/crypto/certificates/README.txt
enebootools/crypto/certificates/__init__.py
enebootools/databaseadmin/__init__.py
enebootools/databaseadmin/dblayer/__init__.py
enebootools/databaseadmin/dblayer/drivers.py
enebootools/extracttool/__init__.py
enebootools/extracttool/extractfunctions.py
enebootools/lib/__init__.py
enebootools/lib/peewee.py
enebootools/lib/utils.py
enebootools/lib/etree/ElementInclude.py
enebootools/lib/etree/ElementPath.py
enebootools/lib/etree/ElementTree.py
enebootools/lib/etree/__init__.py
enebootools/lib/etree/cElementTree.py
enebootools/mergetool/__init__.py
enebootools/mergetool/flpatchapipy.py
enebootools/mergetool/flpatchdir.py
enebootools/mergetool/flpatchlxml.py
enebootools/mergetool/flpatchmodel.py
enebootools/mergetool/flpatchpy.py
enebootools/mergetool/flpatchqs.py
enebootools/mergetool/flpatchtest.py
enebootools/mergetool/flpatchxml.py
enebootools/mergetool/projectbuilder.py
enebootools/mergetool/etc/__init__.py
enebootools/mergetool/etc/index.xml
enebootools/mergetool/etc/formats/__init__.py
enebootools/mergetool/etc/formats/aq23-kut.xml
enebootools-2.4.1.dist-info/licenses/AUTHORS
enebootools-2.4.1.dist-info/licenses/LICENSE.gplv3
enebootools-2.4.1.dist-info/METADATA
enebootools-2.4.1.dist-info/WHEEL
enebootools-2.4.1.dist-info/entry_points.txt
enebootools-2.4.1.dist-info/top_level.txt
enebootools-2.4.1.dist-info/RECORD
