Metadata-Version: 2.4
Name: enebootools
Version: 2.4.1
Summary: ERP tools for Eneboo
Home-page: https://github.com/aulla/eneboo-tools
Author: David Martínez Martí, José A. Fernández Fernández
Author-email: deavidsedice@gmail.com, aullasistemas@gmail.com
Keywords: erp pineboo eneboo tools
Classifier: Development Status :: 4 - Beta
Classifier: License :: OSI Approved :: MIT License
Classifier: Programming Language :: Python :: 3 :: Only
Classifier: Programming Language :: Python :: 3
Classifier: Programming Language :: Python :: 3.6
Classifier: Programming Language :: Python :: 3.7
Classifier: Programming Language :: Python :: 3.8
Classifier: Programming Language :: Python :: 3.9
Classifier: Environment :: X11 Applications :: Qt
Classifier: Topic :: Office/Business :: Financial :: Accounting
Classifier: Typing :: Typed
Classifier: Intended Audience :: End Users/Desktop
Classifier: Intended Audience :: Developers
Classifier: Natural Language :: English
Classifier: Natural Language :: Spanish
Classifier: Operating System :: OS Independent
Requires-Python: >=3.6.9
License-File: LICENSE.gplv3
License-File: AUTHORS
Requires-Dist: lxml
Requires-Dist: watchdog
Dynamic: author
Dynamic: author-email
Dynamic: classifier
Dynamic: description
Dynamic: description-content-type
Dynamic: home-page
Dynamic: keywords
Dynamic: license-file
Dynamic: requires-dist
Dynamic: requires-python
Dynamic: summary
